test_failure_llm/__init__.py
test_failure_llm/analyzer.py
test_failure_llm/model.py
test_failure_llm/train.py
test_failure_llm/training_data.json
test_failure_llm-0.1.7.dist-info/METADATA
test_failure_llm-0.1.7.dist-info/WHEEL
test_failure_llm-0.1.7.dist-info/entry_points.txt
test_failure_llm-0.1.7.dist-info/top_level.txt
test_failure_llm-0.1.7.dist-info/RECORD
