Metadata-Version: 2.4
Name: test_failure_llm
Version: 0.1.7
Summary: A Multimodal LLM from scratch for analyzing test failures.
Author: Antigravity
Requires-Dist: torch
Requires-Dist: torchvision
Requires-Dist: pillow
Requires-Dist: easyocr
Dynamic: author
Dynamic: description
Dynamic: description-content-type
Dynamic: requires-dist
Dynamic: summary
